tls_client.py
veeder_root_tls_socket_library/__init__.py
veeder_root_tls_socket_library/format.py
veeder_root_tls_socket_library/socket.py
veeder_root_tls_socket_library/tls_3xx.py
veeder_root_tls_socket_library-1.0.5.dist-info/LICENSE
veeder_root_tls_socket_library-1.0.5.dist-info/METADATA
veeder_root_tls_socket_library-1.0.5.dist-info/WHEEL
veeder_root_tls_socket_library-1.0.5.dist-info/top_level.txt
veeder_root_tls_socket_library-1.0.5.dist-info/RECORD
