Metadata-Version: 2.2
Name: veeder_root_tls_socket_library
Version: 1.0.5
Summary: Socket library for querying and extracting data from Veeder-Root TLS systems.
Author-email: Evan Redden <redden.evan@gmail.com>
License: MIT License
Project-URL: Homepage, https://github.com/eredden/Veeder-Root-TLS-Socket-Library
Classifier: Programming Language :: Python :: 3
Classifier: License :: OSI Approved :: MIT License
Classifier: Operating System :: OS Independent
Requires-Python: >=3.10
License-File: LICENSE
